pmpy/MovingEntity.py
pmpy/__init__.py
pmpy/abs.py
pmpy/consim.py
pmpy/des.py
pmpy/dist.py
pmpy/mcs.py
pmpy-1.0.24.dist-info/LICENSE
pmpy-1.0.24.dist-info/METADATA
pmpy-1.0.24.dist-info/WHEEL
pmpy-1.0.24.dist-info/top_level.txt
pmpy-1.0.24.dist-info/RECORD
