Metadata-Version: 2.1
Name: pmpy
Version: 1.0.24
Summary: Project Management for Python.
Home-page: https://github.com/Project-PmPy
Author: Naima Sadeghi, Pedram Elmi
Author-email: <naima.sadeghi@gmail.com>, <pedram.elmi@gmail.com>
License: MIT License
Keywords: python,project management,construction,simulation
Classifier: Development Status :: 5 - Production/Stable
Classifier: Environment :: Console
Classifier: Intended Audience :: Developers
Classifier: Intended Audience :: Education
Classifier: Intended Audience :: Science/Research
Classifier: License :: OSI Approved :: MIT License
Classifier: Natural Language :: English
Classifier: Operating System :: OS Independent
Classifier: Programming Language :: Python
Classifier: Programming Language :: Python :: 3
Classifier: Programming Language :: Python :: 3.6
Classifier: Programming Language :: Python :: 3.7
Classifier: Programming Language :: Python :: 3.8
Classifier: Programming Language :: Python :: 3.9
Classifier: Programming Language :: Python :: 3.10
Classifier: Programming Language :: Python :: Implementation :: CPython
Classifier: Programming Language :: Python :: Implementation :: PyPy
Classifier: Topic :: Scientific/Engineering
Requires-Python: >=3.6
License-File: LICENSE
Requires-Dist: simpy (>=4)
Requires-Dist: pandas (>=1)
Requires-Dist: numpy (>=1)
Requires-Dist: scipy (>=1)
Requires-Dist: matplotlib (>=3)
